[
  {
    "processDefinition": {
      "id": 1,
      "code": 7362564936288,
      "name": "BURIED-POINT-BEHAVIOR-PROCESS",
      "version": 14,
      "releaseState": "ONLINE",
      "projectCode": 7359611481056,
      "description": "埋点行为加工",
      "globalParams": "[{\"prop\":\"date8\",\"value\":\"$[yyyyMMdd-1]\",\"direct\":\"IN\",\"type\":\"VARCHAR\"}]",
      "globalParamList": [
        {
          "prop": "date8",
          "direct": "IN",
          "type": "VARCHAR",
          "value": "$[yyyyMMdd-1]"
        }
      ],
      "globalParamMap": {
        "date8": "$[yyyyMMdd-1]"
      },
      "createTime": "2022-10-28 09:47:19",
      "updateTime": "2022-10-31 11:33:13",
      "flag": "YES",
      "userId": 2,
      "userName": null,
      "projectName": null,
      "locations": "[{\"taskCode\":7362497502304,\"x\":160,\"y\":74},{\"taskCode\":7362733263328,\"x\":530,\"y\":74},{\"taskCode\":7362751513440,\"x\":900,\"y\":74}]",
      "scheduleReleaseState": null,
      "timeout": 0,
      "tenantId": 2,
      "tenantCode": null,
      "modifyBy": null,
      "warningGroupId": 0,
      "executionType": "PARALLEL"
    },
    "processTaskRelationList": [
      {
        "id": 228,
        "name": "",
        "processDefinitionVersion": 14,
        "projectCode": 7359611481056,
        "processDefinitionCode": 7362564936288,
        "preTaskCode": 0,
        "preTaskVersion": 0,
        "postTaskCode": 7362497502304,
        "postTaskVersion": 2,
        "conditionType": "NONE",
        "conditionParams": {},
        "createTime": "2022-10-31 11:33:13",
        "updateTime": "2022-10-31 11:33:13",
        "operator": 1,
        "operateTime": "2022-10-31 11:33:13"
      },
      {
        "id": 229,
        "name": "",
        "processDefinitionVersion": 14,
        "projectCode": 7359611481056,
        "processDefinitionCode": 7362564936288,
        "preTaskCode": 7362497502304,
        "preTaskVersion": 2,
        "postTaskCode": 7362733263328,
        "postTaskVersion": 2,
        "conditionType": "NONE",
        "conditionParams": {},
        "createTime": "2022-10-31 11:33:13",
        "updateTime": "2022-10-31 11:33:13",
        "operator": 1,
        "operateTime": "2022-10-31 11:33:13"
      },
      {
        "id": 230,
        "name": "",
        "processDefinitionVersion": 14,
        "projectCode": 7359611481056,
        "processDefinitionCode": 7362564936288,
        "preTaskCode": 7362733263328,
        "preTaskVersion": 2,
        "postTaskCode": 7362751513440,
        "postTaskVersion": 3,
        "conditionType": "NONE",
        "conditionParams": {},
        "createTime": "2022-10-31 11:33:13",
        "updateTime": "2022-10-31 11:33:13",
        "operator": 1,
        "operateTime": "2022-10-31 11:33:13"
      }
    ],
    "taskDefinitionList": [
      {
        "id": 107,
        "code": 7362497502304,
        "name": "埋点行为加工",
        "version": 2,
        "description": "埋点行为加工",
        "projectCode": 7359611481056,
        "userId": 2,
        "taskType": "SQL",
        "taskParams": {
          "localParams": [],
          "resourceList": [],
          "type": "HIVE",
          "datasource": 5,
          "sql": "INSERT overwrite table bpd_db_sim.dtpf_ipc_cust_evt_cnt_d_7\r\nselect \r\nusr_id \r\n,'APPLET'\r\n,'1'\r\n,device_id \r\n,'hit_advert'\r\n,'hit_advert'\r\n,count(*)\r\n,dt \r\n,dt \r\nfrom bpd_db_sim.t2_buried_point_new\r\ngroup by usr_id,device_id,dt",
          "sqlType": "1",
          "preStatements": [],
          "postStatements": [],
          "segmentSeparator": "",
          "displayRows": 10,
          "udfs": ""
        },
        "taskParamList": [],
        "taskParamMap": null,
        "flag": "YES",
        "taskPriority": "MEDIUM",
        "userName": null,
        "projectName": null,
        "workerGroup": "default",
        "environmentCode": -1,
        "failRetryTimes": 0,
        "failRetryInterval": 1,
        "timeoutFlag": "CLOSE",
        "timeoutNotifyStrategy": "WARN",
        "timeout": 0,
        "delayTime": 0,
        "resourceIds": "",
        "createTime": "2022-10-28 09:47:19",
        "updateTime": "2022-10-31 09:29:21",
        "modifyBy": null,
        "taskGroupId": 0,
        "taskGroupPriority": 0,
        "cpuQuota": -1,
        "memoryMax": -1,
        "taskExecuteType": "BATCH",
        "operator": 1,
        "operateTime": "2022-10-31 09:29:21"
      },
      {
        "id": 108,
        "code": 7362733263328,
        "name": "删除当天分区",
        "version": 2,
        "description": "删除当天分区",
        "projectCode": 7359611481056,
        "userId": 2,
        "taskType": "SQL",
        "taskParams": {
          "localParams": [],
          "resourceList": [],
          "type": "POSTGRESQL",
          "datasource": 4,
          "sql": "delete from sim_db_schema.dtpf_ipc_cust_evt_cnt_d_7 where date_dt = '${date8}'",
          "sqlType": "1",
          "preStatements": [],
          "postStatements": [],
          "segmentSeparator": "",
          "displayRows": 10
        },
        "taskParamList": [],
        "taskParamMap": null,
        "flag": "YES",
        "taskPriority": "MEDIUM",
        "userName": null,
        "projectName": null,
        "workerGroup": "default",
        "environmentCode": -1,
        "failRetryTimes": 0,
        "failRetryInterval": 1,
        "timeoutFlag": "CLOSE",
        "timeoutNotifyStrategy": "WARN",
        "timeout": 0,
        "delayTime": 0,
        "resourceIds": "",
        "createTime": "2022-10-28 10:12:46",
        "updateTime": "2022-10-31 09:29:21",
        "modifyBy": null,
        "taskGroupId": 0,
        "taskGroupPriority": 0,
        "cpuQuota": -1,
        "memoryMax": -1,
        "taskExecuteType": "BATCH",
        "operator": 1,
        "operateTime": "2022-10-31 09:29:21"
      },
      {
        "id": 109,
        "code": 7362751513440,
        "name": "埋点行为导出",
        "version": 3,
        "description": "埋点行为导出",
        "projectCode": 7359611481056,
        "userId": 2,
        "taskType": "SHELL",
        "taskParams": {
          "localParams": [],
          "rawScript": "sqoop export \\\r\n--connect jdbc:postgresql://192.168.65.13:5432/dtpf_label_db_sim \\\r\n--username postgres \\\r\n--password postgres1234#@! \\\r\n--table dtpf_ipc_cust_evt_cnt_d_7 \\\r\n--export-dir /user/hive/warehouse/bpd_db_sim.db/dtpf_ipc_cust_evt_cnt_d_7/ \\\r\n--fields-terminated-by '\\001' \\\r\n--m 1 \\\r\n-- --schema sim_db_schema;",
          "resourceList": []
        },
        "taskParamList": [],
        "taskParamMap": null,
        "flag": "YES",
        "taskPriority": "MEDIUM",
        "userName": null,
        "projectName": null,
        "workerGroup": "default",
        "environmentCode": -1,
        "failRetryTimes": 0,
        "failRetryInterval": 1,
        "timeoutFlag": "CLOSE",
        "timeoutNotifyStrategy": "WARN",
        "timeout": 0,
        "delayTime": 0,
        "resourceIds": "",
        "createTime": "2022-10-28 10:12:46",
        "updateTime": "2022-10-31 09:29:21",
        "modifyBy": null,
        "taskGroupId": 0,
        "taskGroupPriority": 0,
        "cpuQuota": -1,
        "memoryMax": -1,
        "taskExecuteType": "BATCH",
        "operator": 1,
        "operateTime": "2022-10-31 09:29:21"
      }
    ],
    "schedule": {
      "id": 1,
      "processDefinitionCode": 7362564936288,
      "processDefinitionName": null,
      "projectName": null,
      "definitionDescription": null,
      "startTime": "2022-11-01 00:00:00",
      "endTime": "2122-11-01 00:00:00",
      "timezoneId": "Asia/Shanghai",
      "crontab": "0 0 1 * * ? *",
      "failureStrategy": "END",
      "warningType": "FAILURE",
      "createTime": "2022-11-01 02:08:41",
      "updateTime": "2022-11-01 02:08:41",
      "userId": 1,
      "userName": null,
      "releaseState": "OFFLINE",
      "warningGroupId": 1,
      "processInstancePriority": "MEDIUM",
      "workerGroup": "default",
      "environmentCode": 7395773982176
    }
  }
]
